odoo8_addon_website_snippet_big_button-8.0.1.0.0.99.dev8-py2.7-nspkg.pth
odoo8_addon_website_snippet_big_button-8.0.1.0.0.99.dev8.dist-info/DESCRIPTION.rst
odoo8_addon_website_snippet_big_button-8.0.1.0.0.99.dev8.dist-info/METADATA
odoo8_addon_website_snippet_big_button-8.0.1.0.0.99.dev8.dist-info/RECORD
odoo8_addon_website_snippet_big_button-8.0.1.0.0.99.dev8.dist-info/WHEEL
odoo8_addon_website_snippet_big_button-8.0.1.0.0.99.dev8.dist-info/metadata.json
odoo8_addon_website_snippet_big_button-8.0.1.0.0.99.dev8.dist-info/namespace_packages.txt
odoo8_addon_website_snippet_big_button-8.0.1.0.0.99.dev8.dist-info/top_level.txt
odoo_addons/website_snippet_big_button/README.rst
odoo_addons/website_snippet_big_button/__init__.py
odoo_addons/website_snippet_big_button/__openerp__.py
odoo_addons/website_snippet_big_button/i18n/es.po
odoo_addons/website_snippet_big_button/i18n/fr.po
odoo_addons/website_snippet_big_button/i18n/pt_BR.po
odoo_addons/website_snippet_big_button/i18n/sl.po
odoo_addons/website_snippet_big_button/i18n/website_snippet_big_button.pot
odoo_addons/website_snippet_big_button/static/description/icon.png
odoo_addons/website_snippet_big_button/static/description/icon.svg
odoo_addons/website_snippet_big_button/static/src/css/website_snippet_big_button.css
odoo_addons/website_snippet_big_button/static/src/css/website_snippet_big_button.css.map
odoo_addons/website_snippet_big_button/static/src/css/website_snippet_big_button.sass
odoo_addons/website_snippet_big_button/static/src/js/website_snippet_big_button.js
odoo_addons/website_snippet_big_button/views/assets.xml
odoo_addons/website_snippet_big_button/views/snippets.xml
